{
	"backtraceGraph" : 
	{
		"commands" : 
		[
			"install"
		],
		"files" : 
		[
			"src/invoice-update-db/CMakeLists.txt"
		],
		"nodes" : 
		[
			{
				"file" : 0
			},
			{
				"command" : 0,
				"file" : 0,
				"line" : 18,
				"parent" : 0
			}
		]
	},
	"installers" : 
	[
		{
			"backtrace" : 1,
			"component" : "Unspecified",
			"destination" : "bin",
			"paths" : 
			[
				"src/invoice-update-db/invoice-update-db"
			],
			"type" : "file"
		}
	],
	"paths" : 
	{
		"build" : "src/invoice-update-db",
		"source" : "src/invoice-update-db"
	}
}
